AutoLinePlotter/__init__.py
AutoLinePlotter/main.py
AutoLinePlotter-0.0.2.dist-info/LICENSE
AutoLinePlotter-0.0.2.dist-info/METADATA
AutoLinePlotter-0.0.2.dist-info/WHEEL
AutoLinePlotter-0.0.2.dist-info/top_level.txt
AutoLinePlotter-0.0.2.dist-info/RECORD
