Metadata-Version: 2.1
Name: AutoLinePlotter
Version: 0.0.2
Summary: This repo support auto line plot for multi-seed event file from TensorBoard
Home-page: https://github.com/Will-Nie/AutoLinePlotter
Author: WillNie; Weiyuhong
Author-email: nieyunpengwill@hotmail.com
License: Apache License, Version 2.0
Classifier: Programming Language :: Python :: 3
Classifier: Operating System :: OS Independent
Requires-Python: >=3.6
License-File: LICENSE
Requires-Dist: numpy
Requires-Dist: tensorboard
Requires-Dist: matplotlib
Requires-Dist: seaborn
Requires-Dist: pandas
Requires-Dist: typing
